odoo/addons/sale_stock_prebook/README.rst
odoo/addons/sale_stock_prebook/__init__.py
odoo/addons/sale_stock_prebook/__manifest__.py
odoo/addons/sale_stock_prebook/hooks.py
odoo/addons/sale_stock_prebook/i18n/it.po
odoo/addons/sale_stock_prebook/i18n/sale_stock_prebook.pot
odoo/addons/sale_stock_prebook/models/__init__.py
odoo/addons/sale_stock_prebook/models/report_stock_forecasted.py
odoo/addons/sale_stock_prebook/models/sale_order.py
odoo/addons/sale_stock_prebook/models/sale_order_line.py
odoo/addons/sale_stock_prebook/models/stock_move.py
odoo/addons/sale_stock_prebook/models/stock_route.py
odoo/addons/sale_stock_prebook/models/stock_rule.py
odoo/addons/sale_stock_prebook/readme/CONTRIBUTORS.rst
odoo/addons/sale_stock_prebook/readme/DESCRIPTION.rst
odoo/addons/sale_stock_prebook/readme/USAGE.rst
odoo/addons/sale_stock_prebook/static/description/icon.png
odoo/addons/sale_stock_prebook/static/description/index.html
odoo/addons/sale_stock_prebook/tests/__init__.py
odoo/addons/sale_stock_prebook/tests/common.py
odoo/addons/sale_stock_prebook/tests/test_sale_stock_prebook.py
odoo/addons/sale_stock_prebook/views/sale_views.xml
odoo/addons/sale_stock_prebook/views/stock_route_views.xml
odoo/addons/sale_stock_prebook/views/stock_rule_views.xml
odoo_addon_sale_stock_prebook-16.0.2.1.0.dist-info/METADATA
odoo_addon_sale_stock_prebook-16.0.2.1.0.dist-info/WHEEL
odoo_addon_sale_stock_prebook-16.0.2.1.0.dist-info/top_level.txt
odoo_addon_sale_stock_prebook-16.0.2.1.0.dist-info/RECORD
