Metadata-Version: 2.1
Name: odoo-addon-sale_stock_prebook
Version: 16.0.2.1.0
Summary: Add process to prebook a sale order's stock before confirming it
Home-page: https://github.com/OCA/sale-prebook
Author: MT Software, BCIM, Odoo Community Association (OCA)
Author-email: support@odoo-community.org
License: LGPL-3
Classifier: Programming Language :: Python
Classifier: Framework :: Odoo
Classifier: Framework :: Odoo :: 16.0
Classifier: License :: OSI Approved :: GNU Lesser General Public License v3 (LGPLv3)
Requires-Python: >=3.10
Requires-Dist: odoo<16.1dev,>=16.0a
